{
  "project_info": {
    "project_number": "118183161980",
    "project_id": "chat-kotlin-88d33",
    "storage_bucket": "chat-kotlin-88d33.firebasestorage.app"
  },
  "client": [
    {
      "client_info": {
        "mobilesdk_app_id": "1:118183161980:android:37dfb65eee8dca823e99f9",
        "android_client_info": {
          "package_name": "com.example.chats_kotlin"
        }
      },
      "oauth_client": [],
      "api_key": [
        {
          "current_key": "AIzaSyBc_2bqiC1BBdK06rcBOOnhyE0OxcQpeow"
        }
      ],
      "services": {
        "appinvite_service": {
          "other_platform_oauth_client": []
        }
      }
    }
  ],
  "configuration_version": "1"
}